{
  "experiment_name": "conv_transformer__q_learning",
  "source_experiment": "conv_transformer",
  "architecture": "conv_transformer+q_learning",
  "best_episode": 72,
  "action_names": [
    "defensive",
    "cautious",
    "rebound",
    "aggressive"
  ],
  "cluster_to_idx": {
    "0": 0,
    "1": 1,
    "2": 2,
    "3": 3
  },
  "agent_config": {
    "episodes": 250,
    "learning_rate": 0.1,
    "discount_factor": 0.95,
    "epsilon_start": 0.3,
    "epsilon_end": 0.02,
    "epsilon_decay": 0.985,
    "include_previous_action": true,
    "eval_interval": 1,
    "random_state": 42,
    "reward_scale": 1.0
  },
  "summary": {
    "experiment_name": "conv_transformer__q_learning",
    "source_experiment": "conv_transformer",
    "architecture": "conv_transformer+q_learning",
    "n_clusters": 4,
    "target_cluster_count": 4,
    "best_mapping": "q_learning_policy(episodes=250,alpha=0.100,gamma=0.950)",
    "objective": "sharpe",
    "best_episode": 72,
    "n_states": 20,
    "n_actions": 4,
    "policy_loaded": false,
    "train_n_days": 1941,
    "train_total_return": 0.03484777503640246,
    "train_annual_return": 0.004457143905122418,
    "train_annual_vol": 0.10222633397382426,
    "train_sharpe": -0.1520435634408785,
    "train_max_drawdown": -0.3136740425868737,
    "train_calmar": 0.014209476399016945,
    "train_final_nav": 103484.77750364025,
    "train_avg_turnover": 0.28871715610510046,
    "train_total_turnover": 560.4,
    "validation_n_days": 555,
    "validation_total_return": 0.4362357562981938,
    "validation_annual_return": 0.17866118606544013,
    "validation_annual_vol": 0.10842534993913933,
    "validation_sharpe": 1.4633218721867063,
    "validation_max_drawdown": -0.07965929695989593,
    "validation_calmar": 2.242816505842202,
    "validation_final_nav": 143623.5756298194,
    "validation_avg_turnover": 0.09081081081081081,
    "validation_total_turnover": 50.4,
    "test_n_days": 278,
    "test_total_return": 0.12064889756254016,
    "test_annual_return": 0.10877370508952322,
    "test_annual_vol": 0.09714548807164548,
    "test_sharpe": 0.9138222150271352,
    "test_max_drawdown": -0.1303934973249583,
    "test_calmar": 0.8341957790919924,
    "test_final_nav": 112064.88975625402,
    "test_avg_turnover": 0.09640287769784171,
    "test_total_turnover": 26.799999999999997
  },
  "q_table_filename": "conv_transformer__q_learning_q_table.csv",
  "q_table_path": "F:\\Documents\\GitHub\\CU_Quant_Trade\\Final_Project\\track_b\\results\\rl_backtest_rankings_k4\\q_tables\\conv_transformer__q_learning_q_table.csv"
}