{
  "experiment_name": "mae_transformer__q_learning",
  "source_experiment": "mae_transformer",
  "architecture": "mae_transformer+q_learning",
  "best_episode": 65,
  "action_names": [
    "defensive",
    "cautious",
    "rebound",
    "aggressive"
  ],
  "cluster_to_idx": {
    "0": 0,
    "1": 1,
    "2": 2,
    "3": 3
  },
  "cluster_label_source": "embeddings_fit_on_train_validation",
  "cluster_fit_splits": "train,validation",
  "cluster_fit_n_windows": 2432,
  "train_risk_free_rate": 0.009641081643265732,
  "policy_train_split": "train",
  "policy_selection_split": "train",
  "agent_config": {
    "episodes": 250,
    "learning_rate": 0.1,
    "discount_factor": 0.95,
    "epsilon_start": 0.3,
    "epsilon_end": 0.02,
    "epsilon_decay": 0.985,
    "include_previous_action": true,
    "eval_interval": 1,
    "random_state": 42,
    "reward_scale": 1.0
  },
  "summary": {
    "experiment_name": "mae_transformer__q_learning",
    "source_experiment": "mae_transformer",
    "architecture": "mae_transformer+q_learning",
    "n_clusters": 4,
    "target_cluster_count": 4,
    "best_mapping": "q_learning_policy(episodes=250,alpha=0.100,gamma=0.950)",
    "objective": "sharpe",
    "best_episode": 65,
    "n_states": 20,
    "n_actions": 4,
    "policy_loaded": false,
    "cluster_label_source": "embeddings_fit_on_train_validation",
    "cluster_fit_splits": "train,validation",
    "cluster_fit_n_windows": 2432,
    "policy_train_split": "train",
    "policy_selection_split": "train",
    "test_only_clusters": "",
    "train_n_days": 1923,
    "train_risk_free_rate": 0.009641081643265732,
    "train_total_return": 0.44100768075709285,
    "train_annual_return": 0.04904100214790574,
    "train_annual_vol": 0.10009368870432227,
    "train_sharpe": 0.3936304178081374,
    "train_max_drawdown": -0.3334201056052307,
    "train_calmar": 0.1470847178183378,
    "train_final_nav": 144100.7680757093,
    "train_avg_turnover": 0.060946437857514295,
    "train_total_turnover": 117.19999999999999,
    "validation_n_days": 508,
    "validation_risk_free_rate": 0.05198248031496063,
    "validation_total_return": -0.032711483262370944,
    "validation_annual_return": -0.016362942350593324,
    "validation_annual_vol": 0.09919716737385116,
    "validation_sharpe": -0.6889856280671391,
    "validation_max_drawdown": -0.1350177210595852,
    "validation_calmar": -0.12119107197322734,
    "validation_final_nav": 96728.85167376291,
    "validation_avg_turnover": 0.4602362204724409,
    "validation_total_turnover": 233.79999999999998,
    "test_n_days": 225,
    "test_risk_free_rate": 0.03992177777777778,
    "test_total_return": 0.11030685095601012,
    "test_annual_return": 0.12433616929153413,
    "test_annual_vol": 0.09729291628821157,
    "test_sharpe": 0.8676314240976695,
    "test_max_drawdown": -0.10247384838777329,
    "test_calmar": 1.2133453680887556,
    "test_final_nav": 111030.68509560102,
    "test_avg_turnover": 0.33066666666666655,
    "test_total_turnover": 74.39999999999998,
    "combined_n_days": 733,
    "combined_risk_free_rate": 0.048280354706684854,
    "combined_total_return": 0.07370414297907724,
    "combined_annual_return": 0.02474995491365073,
    "combined_annual_vol": 0.09858625040517771,
    "combined_sharpe": -0.23867831159342193,
    "combined_max_drawdown": -0.1350177210595852,
    "combined_calmar": 0.18330893692634784,
    "combined_final_nav": 107370.41429790773,
    "combined_avg_turnover": 0.4147339699863574,
    "combined_total_turnover": 304.0
  },
  "q_table_filename": "mae_transformer__q_learning_q_table.csv",
  "q_table_path": "F:\\Documents\\GitHub\\CU_Quant_Trade\\Final_Project\\track_b\\results\\rl_backtest_rankings_k4\\q_tables\\mae_transformer__q_learning_q_table.csv"
}